fsort.py
fsort-0.1.2.dist-info/entry_points.txt
fsort-0.1.2.dist-info/WHEEL
fsort-0.1.2.dist-info/METADATA
fsort-0.1.2.dist-info/RECORD
