Metadata-Version: 2.1
Name: fsort
Version: 0.1.2
Summary: Cli util to sort large files
Home-page: UNKNOWN
License: UNKNOWN
Author: a.opalev
Author-email: levisolympus@gmail.com
Requires-Python: >=3.5
Classifier: License :: OSI Approved :: MIT License
Requires-Dist: click>=7.1.2
